scripts/planner_dataset/generate_dataset.py
scripts/planner_dataset/planner_dataset.csv
scripts/swe_bench/code_edit_dataset/generate_bad_bash_responses.py
scripts/swe_bench/code_edit_dataset/generate_bad_responses.py
scripts/swe_bench/code_edit_dataset/generate_bash_dataset.py
scripts/swe_bench/code_edit_dataset/generate_dataset.py
scripts/swe_bench/code_edit_dataset/train_dpo.py
scripts/swe_bench/evaluation/repo_manager.py
scripts/swe_bench/evaluation/run_evaluation.py
scripts/swe_bench/evaluation/yaaaf_runner.py
scripts/swe_bench/evaluation/swe_bench_workspace/repos/astropy__astropy/conftest.py
scripts/swe_bench/evaluation/swe_bench_workspace/repos/astropy__astropy/setup.py
scripts/swe_bench/evaluation/swe_bench_workspace/repos/astropy__astropy/astropy/__init__.py
scripts/swe_bench/evaluation/swe_bench_workspace/repos/astropy__astropy/astropy/_version.py
scripts/swe_bench/evaluation/swe_bench_workspace/repos/astropy__astropy/astropy/conftest.py
scripts/swe_bench/evaluation/swe_bench_workspace/repos/astropy__astropy/astropy/logger.py
scripts/swe_bench/evaluation/swe_bench_workspace/repos/astropy__astropy/astropy/version.py
scripts/swe_bench/evaluation/swe_bench_workspace/repos/astropy__astropy/astropy/_dev/__init__.py
scripts/swe_bench/evaluation/swe_bench_workspace/repos/astropy__astropy/astropy/_dev/scm_version.py
scripts/swe_bench/evaluation/swe_bench_workspace/repos/astropy__astropy/astropy/_erfa/__init__.py
scripts/swe_bench/evaluation/swe_bench_workspace/repos/astropy__astropy/astropy/config/__init__.py
scripts/swe_bench/evaluation/swe_bench_workspace/repos/astropy__astropy/astropy/config/affiliated.py
scripts/swe_bench/evaluation/swe_bench_workspace/repos/astropy__astropy/astropy/config/configuration.py
scripts/swe_bench/evaluation/swe_bench_workspace/repos/astropy__astropy/astropy/config/paths.py
scripts/swe_bench/evaluation/swe_bench_workspace/repos/astropy__astropy/astropy/config/tests/__init__.py
yaaaf-0.1.6.dist-info/METADATA
yaaaf-0.1.6.dist-info/WHEEL
yaaaf-0.1.6.dist-info/entry_points.txt
yaaaf-0.1.6.dist-info/top_level.txt
yaaaf-0.1.6.dist-info/RECORD
