Metadata-Version: 2.4
Name: yaaaf
Version: 0.1.6
Summary: YAAAF (Yet Another Autonomous Agents Framework) - A modular framework for building intelligent agentic applications with Python backend and Next.js frontend
Author: fractalego
Maintainer: fractalego
License: MIT
Project-URL: Homepage, https://github.com/fractalego/yaaaf
Project-URL: Documentation, https://yaaaf.readthedocs.io
Project-URL: Repository, https://github.com/fractalego/yaaaf.git
Project-URL: Issues, https://github.com/fractalego/yaaaf/issues
Keywords: ai,agents,framework,orchestrator,chatbot,sql,visualization,web-search
Classifier: Development Status :: 3 - Alpha
Classifier: Intended Audience :: Developers
Classifier: License :: OSI Approved :: MIT License
Classifier: Programming Language :: Python :: 3.11
Classifier: Topic :: Software Development :: Libraries :: Python Modules
Classifier: Topic :: Scientific/Engineering :: Artificial Intelligence
Classifier: Topic :: Internet :: WWW/HTTP :: Dynamic Content
Requires-Python: >=3.11
Requires-Dist: bs4>=0.0.2
Requires-Dist: build>=1.2.2.post1
Requires-Dist: duckduckgo-search>=8.0.2
Requires-Dist: fastapi>=0.115.0
Requires-Dist: matplotlib>=3.5.0
Requires-Dist: mdpd>=0.2.1
Requires-Dist: nltk>=3.9.1
Requires-Dist: openpyxl>=3.1.5
Requires-Dist: pandas>=1.3.0
Requires-Dist: pydantic>=2.0.0
Requires-Dist: pydantic-ai>=0.2.18
Requires-Dist: pydantic-settings>=2.8.1
Requires-Dist: pypdf2>=3.0.1
Requires-Dist: rank-bm25>=0.2.2
Requires-Dist: requests>=2.25.0
Requires-Dist: scikit-learn>=1.0.0
Requires-Dist: singleton-decorator>=1.0.0
Requires-Dist: tabulate>=0.8.0
Requires-Dist: uvicorn>=0.15.0
Provides-Extra: dev
Requires-Dist: ruff>=0.1.0; extra == "dev"
Requires-Dist: pytest>=6.0.0; extra == "dev"
Requires-Dist: pytest-asyncio>=0.18.0; extra == "dev"
Provides-Extra: mcp
Requires-Dist: pydantic-ai>=0.2.0; extra == "mcp"
Requires-Dist: pydantic-ai-slim[mcp]>=0.0.50; extra == "mcp"
Provides-Extra: nlp
Requires-Dist: nltk>=3.6.0; extra == "nlp"
Requires-Dist: rank-bm25>=0.2.0; extra == "nlp"
Provides-Extra: all
Requires-Dist: yaaaf[dev,mcp,nlp]; extra == "all"
